area_detector_handlers/__init__.py
area_detector_handlers/_version.py
area_detector_handlers/_xspress3.py
area_detector_handlers/eiger.py
area_detector_handlers/handlers.py
area_detector_handlers/spe_reader.py
area_detector_handlers/tests/__init__.py
area_detector_handlers/tests/conftest.py
area_detector_handlers/tests/test_eiger.py
area_detector_handlers/tests/test_entrypoints.py
area_detector_handlers/tests/test_examples.py
area_detector_handlers/tests/test_hdf5.py
area_detector_handlers/tests/test_imm.py
area_detector_handlers/tests/test_tiff.py
area_detector_handlers/tests/test_xs3.py
area_detector_handlers/tests/data/B020_bluesky_demo_00001-00021.imm
area_detector_handlers-0.0.10.dist-info/AUTHORS.rst
area_detector_handlers-0.0.10.dist-info/LICENSE
area_detector_handlers-0.0.10.dist-info/METADATA
area_detector_handlers-0.0.10.dist-info/WHEEL
area_detector_handlers-0.0.10.dist-info/entry_points.txt
area_detector_handlers-0.0.10.dist-info/top_level.txt
area_detector_handlers-0.0.10.dist-info/RECORD
