Metadata-Version: 2.1
Name: area-detector-handlers
Version: 0.0.10
Summary: DataBroker 'handlers' for Area Detector
Home-page: https://github.com/danielballan/area-detector-handlers
Author: Brookhaven National Lab
Author-email: dallan@bnl.gov
License: BSD (3-clause)
Platform: UNKNOWN
Classifier: Development Status :: 2 - Pre-Alpha
Classifier: Natural Language :: English
Classifier: Programming Language :: Python :: 3
Requires-Python: >=3.6
License-File: LICENSE
License-File: AUTHORS.rst
Requires-Dist: dask[array]
Requires-Dist: h5py
Requires-Dist: pandas
Requires-Dist: tifffile (>=2020.8.25)
